pignacio_scripts/__init__.py
pignacio_scripts/terminal/color.py
pignacio_scripts/terminal/__init__.py
pignacio_scripts/nagios/__init__.py
pignacio_scripts/nagios/logger.py
pignacio_scripts/namedtuple/__init__.py
pignacio_scripts/namedtuple/nt_with_defaults.py
pignacio_scripts/namedtuple/mock_nt.py
pignacio_scripts/python_snippets/__init__.py
pignacio_scripts/python_snippets/snippets.py
pignacio_scripts/pylint_extra/__init__.py
pignacio_scripts/pylint_extra/transforms/__init__.py
pignacio_scripts/testing/mock.py
pignacio_scripts/testing/capture.py
pignacio_scripts/testing/__init__.py
pignacio_scripts/testing/testcase.py
pignacio_scripts-0.0.3.dist-info/DESCRIPTION.rst
pignacio_scripts-0.0.3.dist-info/METADATA
pignacio_scripts-0.0.3.dist-info/WHEEL
pignacio_scripts-0.0.3.dist-info/metadata.json
pignacio_scripts-0.0.3.dist-info/RECORD
pignacio_scripts-0.0.3.dist-info/top_level.txt
