Metadata-Version: 2.0
Name: pignacio-scripts
Version: 0.0.3
Summary: Reusable python scripts and snippets I find useful
Home-page: https://github.com/pignacio/pignacio_scripts
Author: Ignacio Rossi
Author-email: rossi.ignacio@gmail.com 
License: LGPLv2.1
Keywords: p,i,g,n,a,c,i,o,_,s,c,r,i,p,t,s
Platform: UNKNOWN
Classifier: Development Status :: 2 - Pre-Alpha
Classifier: Intended Audience :: Developers
Classifier: License :: OSI Approved :: GNU Lesser General Public License v2 or later (LGPLv2+)
Classifier: Natural Language :: English
Classifier: Programming Language :: Python :: 2
Classifier: Programming Language :: Python :: 2.7
Classifier: Programming Language :: Python :: 3
Classifier: Programming Language :: Python :: 3.3
Classifier: Programming Language :: Python :: 3.4
Requires-Dist: six
